hei_calculator/__init__.py
hei_calculator/hei.py
hei_calculator-0.1.5.dist-info/licenses/LICENSE
hei_calculator-0.1.5.dist-info/METADATA
hei_calculator-0.1.5.dist-info/WHEEL
hei_calculator-0.1.5.dist-info/top_level.txt
hei_calculator-0.1.5.dist-info/RECORD
