Metadata-Version: 2.4
Name: hei-calculator
Version: 0.1.5
Summary: A Python package to calculate Healthy Eating Index (HEI-2015) scores from dietary intake data.
Home-page: https://github.com/nirajang20/HEI
Author: Nirajan Ghimire
Author-email: Nirajan Ghimire <nirajanghimire20@gmail.com>
License: MIT
Project-URL: Homepage, https://github.com/yourusername/hei-calculator
Requires-Python: >=3.8
License-File: LICENSE
Requires-Dist: pandas
Dynamic: license-file
